LICENSE.txt
README.rst
pyproject.toml
setup.cfg
setup.py
tox.ini
composition_stats/__init__.py
composition_stats/conftest.py
composition_stats.egg-info/PKG-INFO
composition_stats.egg-info/SOURCES.txt
composition_stats.egg-info/dependency_links.txt
composition_stats.egg-info/requires.txt
composition_stats.egg-info/top_level.txt
composition_stats/tests/__init__.py
composition_stats/tests/test_composition.py
docs/Makefile
docs/conf.py
docs/index.rst
docs/make.bat
licenses/scikit-bio.txt