Metadata-Version: 2.1
Name: composition-stats
Version: 2.0.0
Summary: compositional data analysis
Home-page: https://github.com/ntessore/composition_stats
Maintainer: Nicolas Tessore
Maintainer-email: n.tessore@ucl.ac.uk
License: BSD-3-Clause
Platform: UNKNOWN
Classifier: Programming Language :: Python :: 3
Classifier: License :: OSI Approved :: BSD License
Classifier: Operating System :: OS Independent
Requires-Python: >=3.6
Provides-Extra: test
Provides-Extra: docs
